{
  "mock": {
    "weather": {
      "today": {
        "санкт-петербург": 10,
        "москва": 12
      },
      "tomorrow": {
        "санкт-петербург": -5,
        "москва": -9
      }
    },
    "poster": {
      "today": {
        "санкт-петербург": [
          {
            "event": "Событие 1",
            "price": 100500,
            "link": "https://example.com/?1"
          },
          {
            "event": "Событие 2",
            "price": 500,
            "link": "https://example.com/?2"
          }
        ],
        "москва": [
          {
            "event": "Событие 3",
            "price": 200,
            "link": "https://example.com/?3"
          },
          {
            "event": "Событие 4",
            "price": 1000,
            "link": "https://example.com/?4"
          }
        ]
      },
      "tomorrow": {
        "санкт-петербург": [
          {
            "event": "Событие 11",
            "price": 111,
            "link": "https://example.com/?11"
          },
          {
            "event": "Событие 12",
            "price": 111500,
            "link": "https://example.com/?12"
          }
        ],
        "москва": [
          {
            "event": "Событие 13",
            "price": 11200,
            "link": "https://example.com/?13"
          },
          {
            "event": "Событие 14",
            "price": 111000,
            "link": "https://example.com/?14"
          }
        ]
      }
    },
    "trafficStatus": {
      "санкт-петербург": 7,
      "москва": 9
    },
    "currency": {
      "USD": 61.77,
      "EUR": 64.99,
      "AUD": 42.08,
      "AZN": 36.34,
      "AMD": 15.63
    }
  },
  "cities": {
    "280209315": "москва",
    "103360899": "санкт-петербург"
  }
}